config_files/__init__.py
config_files/validator.py
config_files_validator-1.5.0.dist-info/LICENSE
config_files_validator-1.5.0.dist-info/METADATA
config_files_validator-1.5.0.dist-info/WHEEL
config_files_validator-1.5.0.dist-info/entry_points.txt
config_files_validator-1.5.0.dist-info/top_level.txt
config_files_validator-1.5.0.dist-info/RECORD
