Metadata-Version: 2.1
Name: config-files-validator
Version: 1.5.0
Summary: A validator for json, yaml, and jinja2 files
Home-page: https://github.com/feffe/config-files-validator
Author: Fredrik Westermark
Author-email: feffe.westermark@gmail.com
License: MIT
Keywords: json yaml jinja2 configuration config template templates validator validation
Platform: UNKNOWN
Classifier: Development Status :: 5 - Production/Stable
Classifier: Topic :: Software Development :: Quality Assurance
Classifier: Intended Audience :: Developers
Classifier: License :: OSI Approved :: MIT License
Requires-Python: >=3.8
License-File: LICENSE
Requires-Dist: pyyaml
Requires-Dist: jinja2
Requires-Dist: toml
Requires-Dist: junit-xml
